statdistwiz/Binomialdistribution.py
statdistwiz/Gaussiandistribution.py
statdistwiz/Generaldistribution.py
statdistwiz/__init__.py
statdistwiz-1.0.0.dist-info/LICENSE
statdistwiz-1.0.0.dist-info/METADATA
statdistwiz-1.0.0.dist-info/WHEEL
statdistwiz-1.0.0.dist-info/top_level.txt
statdistwiz-1.0.0.dist-info/RECORD
