Metadata-Version: 2.1
Name: statdistwiz
Version: 1.0.0
Summary: Probability Distribution Package
Author-email: Natasha Techwiz <natasha.techwiz@gmail.com>
Keywords: probability,gaussian distribution,binomial distribution,statistics,mean,standard deviation,PDF,PMF
Classifier: License :: OSI Approved :: MIT License
Classifier: Programming Language :: Python
Classifier: Programming Language :: Python :: 3
Requires-Python: >=3.9
License-File: LICENSE
Requires-Dist: matplotlib
